ingradient_library/__init__.py
ingradient_library/active_contour_loss.py
ingradient_library/data_augmentation.py
ingradient_library/data_oganizer.py
ingradient_library/data_organizer.py
ingradient_library/dataloads.py
ingradient_library/deep_supervision_loss.py
ingradient_library/dice_loss.py
ingradient_library/get_imbalance_weight.py
ingradient_library/get_information.py
ingradient_library/get_nnunet_setting.py
ingradient_library/inference.py
ingradient_library/loss.py
ingradient_library/lr_scheduler.py
ingradient_library/maic.py
ingradient_library/main.py
ingradient_library/medical_decathlon_organizer.py
ingradient_library/model.py
ingradient_library/nnunet_3D_run.py
ingradient_library/optimizer.py
ingradient_library/patch_transform.py
ingradient_library/preprocessing.py
ingradient_library/reversible_backbone.py
ingradient_library/sampling.py
ingradient_library/trainer.py
ingradient_library/training_example.py
ingradient_library/transform.py
ingradient_library/unet.py
ingradient_library/visualization.py
ingradient_lib_temp2-0.6.61.dist-info/METADATA
ingradient_lib_temp2-0.6.61.dist-info/WHEEL
ingradient_lib_temp2-0.6.61.dist-info/top_level.txt
ingradient_lib_temp2-0.6.61.dist-info/RECORD
