Metadata-Version: 2.1
Name: ingradient-lib-temp2
Version: 0.6.61
Summary: Medical Deep Learning Framework.
Home-page: https://github.com/InGradient/InGradient_AI_Library
Author: seungyeob.seon
Author-email: liamseon@gmail.com
License: MIT
Keywords: pypi deploy
Platform: UNKNOWN
Requires-Dist: SimpleITK
Requires-Dist: revlib
